volcano/arch/__init__.py
volcano/arch/__main__.py
volcano/arch/archive.py
volcano/arch/file_writer.py
volcano/arch/super_queue.py
volcano_arch-1.1.dist-info/LICENSE
volcano_arch-1.1.dist-info/METADATA
volcano_arch-1.1.dist-info/WHEEL
volcano_arch-1.1.dist-info/top_level.txt
volcano_arch-1.1.dist-info/RECORD
